{
    "unique_id": "a3f439db-fbcb-5c73-879c-413384a07a74",
    "title": "Supporting sustainability, digital health, and the future of work",
    "summary": "MIT och Accenture Convergence Initiative for Industry and Technology har valt ut tre nya forskningsprojekt som kommer att f\u00e5 st\u00f6d fr\u00e5n initiativet. Forskningsprojekten syftar till att accelerera framsteg f\u00f6r att m\u00f6ta komplexa samh\u00e4llsbehov genom nya insikter om f\u00f6retagskonvergens inom teknik och innovation. Projekten fokuserar p\u00e5 h\u00e5llbarhet, digital h\u00e4lsa och framtidens arbete. Genom att samla tekniska experter fr\u00e5n n\u00e4ringslivet och akademin vill initiativet fr\u00e4mja kunskapsutbyte och l\u00e4rande. Projekten kommer att unders\u00f6ka hur industriella kluster kan bidra till att minska koldioxidutsl\u00e4pp, bek\u00e4mpa barndomsfetma och forma framtidens arbetsmarknad med hj\u00e4lp av AI och dataanalys.",
    "link": "https://news.mit.edu/2023/supporting-sustainability-digital-health-future-work-0824",
    "published": "2023-08-24"
}