{
    "unique_id": "78aa693a-33f8-5329-841d-6862accc0db7",
    "title": "Gamifying medical data labeling to advance AI",
    "summary": "Erik Duhaime, en tidigare doktorand vid MIT:s Center for Collective Intelligence, grundade Centaur Labs och utvecklade appen DiagnosUs f\u00f6r att samla in \u00e5sikter fr\u00e5n medicinska experter om vetenskapliga och biomedicinska data. Genom appen kan anv\u00e4ndare granska bilder av potentiellt cancerframkallande hudlesioner eller ljudklipp av hj\u00e4rt- och lungljud som kan indikera problem. Om anv\u00e4ndarna \u00e4r korrekta anv\u00e4nder Centaur deras \u00e5sikter och bel\u00f6nar dem med sm\u00e5 kontantpriser. Dessa \u00e5sikter hj\u00e4lper sedan medicinska AI-f\u00f6retag att tr\u00e4na och f\u00f6rb\u00e4ttra sina algoritmer. Centaur Labs kombinerar medicinska experternas \u00f6nskan att f\u00f6rb\u00e4ttra sina f\u00e4rdigheter med behovet av v\u00e4ldefinierade medicinska data f\u00f6r AI-f\u00f6retag inom bioteknik, l\u00e4kemedelsutveckling och medicinteknik.",
    "link": "https://news.mit.edu/2023/gamifying-medical-data-labeling-ai-0628",
    "published": "2023-06-28"
}